[{"name":"swagger_dart_code_generator","qualifiedName":"swagger_dart_code_generator","href":"swagger_dart_code_generator/swagger_dart_code_generator-library.html","type":"library","overriddenDepth":0},{"name":"SwaggerDartCodeGenerator","qualifiedName":"swagger_dart_code_generator.SwaggerDartCodeGenerator","href":"swagger_dart_code_generator/SwaggerDartCodeGenerator-class.html","type":"class","overriddenDepth":0,"enclosedBy":{"name":"swagger_dart_code_generator","type":"library"}},{"name":"SwaggerDartCodeGenerator","qualifiedName":"swagger_dart_code_generator.SwaggerDartCodeGenerator.SwaggerDartCodeGenerator","href":"swagger_dart_code_generator/SwaggerDartCodeGenerator/SwaggerDartCodeGenerator.html","type":"constructor","overriddenDepth":0,"enclosedBy":{"name":"SwaggerDartCodeGenerator","type":"class"}},{"name":"build","qualifiedName":"swagger_dart_code_generator.SwaggerDartCodeGenerator.build","href":"swagger_dart_code_generator/SwaggerDartCodeGenerator/build.html","type":"method","overriddenDepth":1,"enclosedBy":{"name":"SwaggerDartCodeGenerator","type":"class"}},{"name":"buildExtensions","qualifiedName":"swagger_dart_code_generator.SwaggerDartCodeGenerator.buildExtensions","href":"swagger_dart_code_generator/SwaggerDartCodeGenerator/buildExtensions.html","type":"property","overriddenDepth":0,"enclosedBy":{"name":"SwaggerDartCodeGenerator","type":"class"}},{"name":"options","qualifiedName":"swagger_dart_code_generator.SwaggerDartCodeGenerator.options","href":"swagger_dart_code_generator/SwaggerDartCodeGenerator/options.html","type":"property","overriddenDepth":0,"enclosedBy":{"name":"SwaggerDartCodeGenerator","type":"class"}},{"name":"generateExtensions","qualifiedName":"swagger_dart_code_generator.generateExtensions","href":"swagger_dart_code_generator/generateExtensions.html","type":"function","overriddenDepth":0,"enclosedBy":{"name":"swagger_dart_code_generator","type":"library"}},{"name":"indexFileName","qualifiedName":"swagger_dart_code_generator.indexFileName","href":"swagger_dart_code_generator/indexFileName-constant.html","type":"top-level constant","overriddenDepth":0,"enclosedBy":{"name":"swagger_dart_code_generator","type":"library"}},{"name":"inputFileExtension","qualifiedName":"swagger_dart_code_generator.inputFileExtension","href":"swagger_dart_code_generator/inputFileExtension-constant.html","type":"top-level constant","overriddenDepth":0,"enclosedBy":{"name":"swagger_dart_code_generator","type":"library"}},{"name":"mappingFileName","qualifiedName":"swagger_dart_code_generator.mappingFileName","href":"swagger_dart_code_generator/mappingFileName-constant.html","type":"top-level constant","overriddenDepth":0,"enclosedBy":{"name":"swagger_dart_code_generator","type":"library"}},{"name":"outputFileExtension","qualifiedName":"swagger_dart_code_generator.outputFileExtension","href":"swagger_dart_code_generator/outputFileExtension-constant.html","type":"top-level constant","overriddenDepth":0,"enclosedBy":{"name":"swagger_dart_code_generator","type":"library"}},{"name":"swaggerCodeBuilder","qualifiedName":"swagger_dart_code_generator.swaggerCodeBuilder","href":"swagger_dart_code_generator/swaggerCodeBuilder.html","type":"function","overriddenDepth":0,"enclosedBy":{"name":"swagger_dart_code_generator","type":"library"}}]
